README.md
setup.py
src/WheneverEverywhere/__init__.py
src/WheneverEverywhere/__main__.py
src/WheneverEverywhere.egg-info/PKG-INFO
src/WheneverEverywhere.egg-info/SOURCES.txt
src/WheneverEverywhere.egg-info/dependency_links.txt
src/WheneverEverywhere.egg-info/top_level.txt
src/WheneverEverywhere/whenever_c_transpiler/__init__.py
src/WheneverEverywhere/whenever_c_transpiler/template.c
src/WheneverEverywhere/whenever_c_transpiler/whenver_c_transpiler.py
src/WheneverEverywhere/whenever_interpreter/QnDio.py
src/WheneverEverywhere/whenever_interpreter/__init__.py
src/WheneverEverywhere/whenever_interpreter/whenever_interpreter.py
src/WheneverEverywhere/whenever_parser/__init__.py
src/WheneverEverywhere/whenever_parser/parsetab.py
src/WheneverEverywhere/whenever_parser/whenever_parser.py