Metadata-Version: 2.1
Name: WheneverEverywhere
Version: 0.0.0a1
Summary: A python-interpreter and compiler for the Whenever language.
Home-page: https://github.com/itruffat/WheneverEverywhere
Author: itruffat
License: UNKNOWN
Platform: UNKNOWN
Classifier: Development Status :: 3 - Alpha
Classifier: Intended Audience :: Developers
Classifier: License :: OSI Approved :: MIT License
Classifier: Programming Language :: Python :: 3
Classifier: Programming Language :: Python :: 3.6
Classifier: Programming Language :: Python :: 3.7
Classifier: Programming Language :: Python :: 3.8
Classifier: Programming Language :: Python :: 3.9
